README.md
setup.cfg
setup.py
chance_orm.egg-info/PKG-INFO
chance_orm.egg-info/SOURCES.txt
chance_orm.egg-info/dependency_links.txt
chance_orm.egg-info/not-zip-safe
chance_orm.egg-info/requires.txt
chance_orm.egg-info/top_level.txt
orm/__init__.py
orm/database.py
orm/session.py
orm/connections/__init__.py
orm/connections/connection.py
orm/connections/influxdb_connection.py
orm/connections/rethinkdb_connection.py
orm/connections/sql_connection.py
tests/__init__.py
tests/test_database.py
tests/test_influxdb_connection.py
tests/test_rethinkdb_connection.py
tests/test_session.py
tests/test_sql_base.py
tests/test_sql_connection.py