Metadata-Version: 1.0
Name: chance-orm
Version: 1.4.2
Summary: The orm for chancefocus
Home-page: https://gitee.com/QianFuFinancial/orm_sqlalchemy.git
Author: Jimin Huang
Author-email: huangjimin@whu.edu.cn
License: MIT
Platform: UNKNOWN
